pyhomogeneity/__init__.py
pyhomogeneity/_version.py
pyhomogeneity/pyhomogeneity.py
pyhomogeneity-1.1.dist-info/LICENSE.txt
pyhomogeneity-1.1.dist-info/METADATA
pyhomogeneity-1.1.dist-info/WHEEL
pyhomogeneity-1.1.dist-info/top_level.txt
pyhomogeneity-1.1.dist-info/RECORD
