Metadata-Version: 2.1
Name: pyhomogeneity
Version: 1.1
Summary: A python package for homogeneity test.
Home-page: https://github.com/mmhs013/pyhomogeneity
Author: Md. Manjurul Hussain Shourov
Author-email: mmhs013@gmail.com
License: MIT
Platform: UNKNOWN
Classifier: Programming Language :: Python :: 2.7
Classifier: Programming Language :: Python :: 3.4
Classifier: Programming Language :: Python :: 3.5
Classifier: Programming Language :: Python :: 3.6
Classifier: Programming Language :: Python :: 3.7
Classifier: Programming Language :: Python :: 3.8
Classifier: License :: OSI Approved :: MIT License
Classifier: Intended Audience :: Science/Research
Classifier: Operating System :: OS Independent
Classifier: Topic :: Scientific/Engineering
Classifier: Development Status :: 5 - Production/Stable
Requires-Dist: numpy
Requires-Dist: scipy
